sam_learner/__init__.py
sam_learner/extended_sam_learner.py
sam_learner/sam_learner.py
sam_learner/core/__init__.py
sam_learner/core/domain_export.py
sam_learner/core/effects_extractor.py
sam_learner/core/extended_predicate_matcher.py
sam_learner/core/grounded_action_locator.py
sam_learner/core/predicates_matcher.py
sam_learner/core/problem_export.py
sam_learner/core/proxy_action_generator.py
sam_learner/core/random_walk_plan_generator.py
sam_learner/core/remote_plan_generator.py
sam_learner/core/trajectories_manager.py
sam_learner/core/trajectory_generator.py
sam_learner/model_validation/__init__.py
sam_learner/model_validation/action_model_statistics_extractor.py
sam_learner/model_validation/action_precision_recall_calculator.py
sam_learner/model_validation/consistent_models_calculator.py
sam_learner/model_validation/domain_comparison.py
sam_learner/model_validation/fast_downward_solver.py
sam_learner/model_validation/learned_domain_validator.py
sam_learner/sam_models/__init__.py
sam_learner/sam_models/comparable_predicate.py
sam_learner/sam_models/grounded_action.py
sam_learner/sam_models/parameter_binding.py
sam_learner/sam_models/state.py
sam_learner/sam_models/trajectory_component.py
sam_learner/sam_models/types.py
sam_learner-2.1.9.dist-info/METADATA
sam_learner-2.1.9.dist-info/WHEEL
sam_learner-2.1.9.dist-info/top_level.txt
sam_learner-2.1.9.dist-info/RECORD
