Metadata-Version: 2.1
Name: sam-learner
Version: 2.1.9
Summary: Safe Action Model Learner
Home-page: UNKNOWN
Author: Argaman Mordoch
License: UNKNOWN
Keywords: automatic safe action model learning
Platform: UNKNOWN
Requires-Python: >=3.8
